[{"cycle": 1, "file": "2232508f01_report_20221121.txt", "pcs_mode": "FINEGUIDE", "visit_type": "PRIME TARGETED FIXED", "start_time": "2022-11-21T01:06:43Z", "duration": "00/01:13:13", "instrument": "MIRI Medium Resolution Spectroscopy", "target": "J045853.89+643452.9", "category": "Star", "keywords": "Brown dwarfs", "program": 1189, "visit": 15, "observation": 1, "parallels": []}, {"cycle": 1, "file": "2232508f01_report_20221121.txt", "pcs_mode": "FINEGUIDE", "visit_type": "PRIME WFSC ROUTINE", "start_time": "2022-11-21T02:32:03Z", "duration": "00/01:32:08", "instrument": "WFSC NIRCam Fine Phasing", "target": "2MASS-05352161+6715458", "category": "Calibration", "keywords": "Focus test", "program": 2586, "visit": 467, "observation": 1, "parallels": []}, {"cycle": 1, "file": "2232508f01_report_20221121.txt", "pcs_mode": "FINEGUIDE", "visit_type": "PRIME TARGETED FIXED", "start_time": "2022-11-21T04:36:46Z", "duration": "00/01:29:19", "instrument": "MIRI Medium Resolution Spectroscopy", "target": "F2M1106-MIRI", "category": "Galaxy", "keywords": "Active galactic nuclei, Emission line galaxies, Quasars", "program": 1335, "visit": 2, "observation": 1, "parallels": [{"cycle": 1, "file": "2232508f01_report_20221121.txt", "pcs_mode": "NONE", "visit_type": "PARALLEL DARK CALIBRATION", "start_time": "^ATTACHED TO PRIME^", "duration": "", "instrument": "NIRSpec Dark", "target": "", "category": "", "keywords": "", "program": 1495, "visit": 99, "observation": 1, "parallels": []}]}, {"cycle": 1, "file": "2232508f01_report_20221121.txt", "pcs_mode": "FINEGUIDE", "visit_type": "PRIME TARGETED FIXED", "start_time": "2022-11-21T06:22:44Z", "duration": "00/00:28:43", "instrument": "MIRI Medium Resolution Spectroscopy", "target": "F2M1106-BG", "category": "Unidentified", "keywords": "Blank field", "program": 1335, "visit": 11, "observation": 1, "parallels": [{"cycle": 1, "file": "2232508f01_report_20221121.txt", "pcs_mode": "NONE", "visit_type": "PARALLEL SLEW CALIBRATION", "start_time": "^ATTACHED TO PRIME^", "duration": "", "instrument": "NIRSpec Internal Lamp", "target": "", "category": "", "keywords": "", "program": 1490, "visit": 30, "observation": 1, "parallels": []}]}, {"cycle": 1, "file": "2232508f01_report_20221121.txt", "pcs_mode": "FINEGUIDE", "visit_type": "PRIME TARGETED FIXED", "start_time": "2022-11-21T07:32:44Z", "duration": "00/01:03:55", "instrument": "MIRI Medium Resolution Spectroscopy", "target": "CASSIOPEIA-A-KNOT1", "category": "ISM", "keywords": "Supernova remnants", "program": 1947, "visit": 4, "observation": 1, "parallels": []}, {"cycle": 1, "file": "2232508f01_report_20221121.txt", "pcs_mode": "FINEGUIDE", "visit_type": "PRIME TARGETED FIXED", "start_time": "2022-11-21T08:43:36Z", "duration": "00/01:03:55", "instrument": "MIRI Medium Resolution Spectroscopy", "target": "CASSIOPEIA-A-KNOT2", "category": "ISM", "keywords": "Supernova remnants", "program": 1947, "visit": 5, "observation": 1, "parallels": []}, {"cycle": 1, "file": "2232508f01_report_20221121.txt", "pcs_mode": "FINEGUIDE", "visit_type": "PRIME TARGETED FIXED", "start_time": "2022-11-21T09:53:42Z", "duration": "00/01:01:10", "instrument": "MIRI Medium Resolution Spectroscopy", "target": "CASSIOPEIA-A-KNOT3", "category": "ISM", "keywords": "Supernova remnants", "program": 1947, "visit": 6, "observation": 1, "parallels": []}, {"cycle": 1, "file": "2232508f01_report_20221121.txt", "pcs_mode": "FINEGUIDE", "visit_type": "PRIME TARGETED FIXED", "start_time": "2022-11-21T11:02:45Z", "duration": "00/01:03:55", "instrument": "MIRI Medium Resolution Spectroscopy", "target": "BACKGROUND-RETURN", "category": "Calibration", "keywords": "Telescope/sky background", "program": 1947, "visit": 7, "observation": 1, "parallels": []}, {"cycle": 1, "file": "2232508f01_report_20221121.txt", "pcs_mode": "MOVING", "visit_type": "PRIME TARGETED MOVING", "start_time": "2022-11-21T12:47:08Z", "duration": "00/01:37:25", "instrument": "MIRI Medium Resolution Spectroscopy", "target": "526-JENA", "category": "Solar System", "keywords": "Asteroid", "program": 1549, "visit": 5, "observation": 1, "parallels": []}, {"cycle": 1, "file": "2232508f01_report_20221121.txt", "pcs_mode": "MOVING", "visit_type": "PRIME TARGETED MOVING", "start_time": "2022-11-21T15:32:55Z", "duration": "00/01:51:36", "instrument": "NIRSpec IFU Spectroscopy", "target": "POLYMELE", "category": "Solar System", "keywords": "Asteroid", "program": 2574, "visit": 5, "observation": 1, "parallels": []}, {"cycle": 1, "file": "2232508f01_report_20221121.txt", "pcs_mode": "FINEGUIDE", "visit_type": "PRIME TARGETED FIXED", "start_time": "2022-11-21T18:31:05Z", "duration": "00/04:01:35", "instrument": "MIRI Imaging", "target": "TRAPPIST-1B", "category": "Star", "keywords": "Exoplanet Systems, Exoplanets, M dwarfs, M stars", "program": 1279, "visit": 6, "observation": 1, "parallels": []}, {"cycle": 1, "file": "2232508f01_report_20221121.txt", "pcs_mode": "FINEGUIDE", "visit_type": "PRIME TARGETED FIXED", "start_time": "2022-11-21T23:42:16Z", "duration": "00/02:42:53", "instrument": "MIRI Medium Resolution Spectroscopy", "target": "SDSSJ0749-MIRI", "category": "Galaxy", "keywords": "Active galactic nuclei, Emission line galaxies, Quasar-galaxy pairs", "program": 2654, "visit": 5, "observation": 1, "parallels": [{"cycle": 1, "file": "2232508f01_report_20221121.txt", "pcs_mode": "NONE", "visit_type": "PARALLEL DARK CALIBRATION", "start_time": "^ATTACHED TO PRIME^", "duration": "", "instrument": "NIRISS Dark", "target": "", "category": "", "keywords": "", "program": 1497, "visit": 19, "observation": 1, "parallels": []}, {"cycle": 1, "file": "2232508f01_report_20221121.txt", "pcs_mode": "NONE", "visit_type": "PARALLEL SLEW CALIBRATION", "start_time": "^ATTACHED TO PRIME^", "duration": "", "instrument": "NIRSpec Internal Lamp", "target": "", "category": "", "keywords": "", "program": 2777, "visit": 146, "observation": 1, "parallels": []}]}, {"cycle": 1, "file": "2232508f01_report_20221121.txt", "pcs_mode": "FINEGUIDE", "visit_type": "PRIME TARGETED FIXED", "start_time": "2022-11-22T02:28:30Z", "duration": "00/00:43:56", "instrument": "MIRI Medium Resolution Spectroscopy", "target": "SDSSJ0749-BG", "category": "Unidentified", "keywords": "Blank field", "program": 2654, "visit": 6, "observation": 1, "parallels": [{"cycle": 1, "file": "2232508f01_report_20221121.txt", "pcs_mode": "NONE", "visit_type": "PARALLEL DARK CALIBRATION", "start_time": "^ATTACHED TO PRIME^", "duration": "", "instrument": "NIRSpec Dark", "target": "", "category": "", "keywords": "", "program": 1495, "visit": 32, "observation": 1, "parallels": []}]}, {"cycle": 1, "file": "2232508f01_report_20221121.txt", "pcs_mode": "FINEGUIDE", "visit_type": "PRIME TARGETED FIXED", "start_time": "2022-11-22T04:19:13Z", "duration": "00/04:39:41", "instrument": "NIRSpec IFU Spectroscopy", "target": "BDF3299", "category": "Galaxy", "keywords": "High-redshift galaxies, Lyman-alpha galaxies", "program": 1893, "visit": 1, "observation": 1, "parallels": [{"cycle": 1, "file": "2232508f01_report_20221121.txt", "pcs_mode": "NONE", "visit_type": "PARALLEL DARK CALIBRATION", "start_time": "^ATTACHED TO PRIME^", "duration": "", "instrument": "NIRISS Dark", "target": "", "category": "", "keywords": "", "program": 1497, "visit": 20, "observation": 1, "parallels": []}, {"cycle": 1, "file": "2232508f01_report_20221121.txt", "pcs_mode": "NONE", "visit_type": "PARALLEL SLEW CALIBRATION", "start_time": "^ATTACHED TO PRIME^", "duration": "", "instrument": "MIRI Anneal", "target": "", "category": "", "keywords": "", "program": 1520, "visit": 22, "observation": 1, "parallels": []}]}, {"cycle": 1, "file": "2232508f01_report_20221121.txt", "pcs_mode": "FINEGUIDE", "visit_type": "PRIME TARGETED FIXED", "start_time": "2022-11-22T09:05:48Z", "duration": "00/00:38:43", "instrument": "NIRSpec IFU Spectroscopy", "target": "BDF3299-BACKGROUND", "category": "Galaxy", "keywords": "High-redshift galaxies", "program": 1893, "visit": 2, "observation": 1, "parallels": []}, {"cycle": 1, "file": "2232508f01_report_20221121.txt", "pcs_mode": "FINEGUIDE", "visit_type": "PRIME TARGETED FIXED", "start_time": "2022-11-22T10:20:55Z", "duration": "00/00:51:06", "instrument": "MIRI Imaging", "target": "NGC-1566", "category": "Galaxy", "keywords": "Spiral galaxies", "program": 2107, "visit": 7, "observation": 1, "parallels": [{"cycle": 1, "file": "2232508f01_report_20221121.txt", "pcs_mode": "NONE", "visit_type": "PARALLEL SLEW CALIBRATION", "start_time": "^ATTACHED TO PRIME^", "duration": "", "instrument": "NIRSpec Internal Lamp", "target": "", "category": "", "keywords": "", "program": 2777, "visit": 121, "observation": 1, "parallels": []}]}, {"cycle": 1, "file": "2232508f01_report_20221121.txt", "pcs_mode": "FINEGUIDE", "visit_type": "PRIME TARGETED FIXED", "start_time": "2022-11-22T11:16:45Z", "duration": "00/00:48:21", "instrument": "MIRI Imaging", "target": "NGC-1566", "category": "Galaxy", "keywords": "Spiral galaxies", "program": 2107, "visit": 7, "observation": 2, "parallels": []}, {"cycle": 1, "file": "2232508f01_report_20221121.txt", "pcs_mode": "FINEGUIDE", "visit_type": "PRIME TARGETED FIXED", "start_time": "2022-11-22T12:09:17Z", "duration": "00/00:48:21", "instrument": "MIRI Imaging", "target": "NGC-1566", "category": "Galaxy", "keywords": "Spiral galaxies", "program": 2107, "visit": 7, "observation": 3, "parallels": []}, {"cycle": 1, "file": "2232508f01_report_20221121.txt", "pcs_mode": "FINEGUIDE", "visit_type": "PRIME TARGETED FIXED", "start_time": "2022-11-22T13:02:22Z", "duration": "00/00:48:21", "instrument": "MIRI Imaging", "target": "NGC-1566", "category": "Galaxy", "keywords": "Spiral galaxies", "program": 2107, "visit": 7, "observation": 4, "parallels": []}, {"cycle": 1, "file": "2232508f01_report_20221121.txt", "pcs_mode": "FINEGUIDE", "visit_type": "PRIME TARGETED FIXED", "start_time": "2022-11-22T14:00:19Z", "duration": "00/01:00:50", "instrument": "NIRCam Imaging", "target": "NGC-1566", "category": "Galaxy", "keywords": "Spiral galaxies", "program": 2107, "visit": 25, "observation": 1, "parallels": [{"cycle": 1, "file": "2232508f01_report_20221121.txt", "pcs_mode": null, "visit_type": "COORDINATED PARALLEL", "start_time": "", "duration": null, "instrument": "MIRI Imaging", "parallels": []}]}, {"cycle": 1, "file": "2232508f01_report_20221121.txt", "pcs_mode": "FINEGUIDE", "visit_type": "PRIME TARGETED FIXED", "start_time": "2022-11-22T15:06:06Z", "duration": "00/00:58:05", "instrument": "NIRCam Imaging", "target": "NGC-1566", "category": "Galaxy", "keywords": "Spiral galaxies", "program": 2107, "visit": 25, "observation": 2, "parallels": [{"cycle": 1, "file": "2232508f01_report_20221121.txt", "pcs_mode": null, "visit_type": "COORDINATED PARALLEL", "start_time": "", "duration": null, "instrument": "MIRI Imaging", "parallels": []}]}, {"cycle": 1, "file": "2232508f01_report_20221121.txt", "pcs_mode": "FINEGUIDE", "visit_type": "PRIME TARGETED FIXED", "start_time": "2022-11-22T16:31:22Z", "duration": "00/00:43:44", "instrument": "MIRI Imaging", "target": "MIRI-PT-5", "category": "Galaxy", "keywords": "High-redshift galaxies, Starburst galaxies, Ultraluminous infrared galaxies", "program": 2516, "visit": 9, "observation": 1, "parallels": [{"cycle": 1, "file": "2232508f01_report_20221121.txt", "pcs_mode": "NONE", "visit_type": "PARALLEL DARK CALIBRATION", "start_time": "^ATTACHED TO PRIME^", "duration": "", "instrument": "NIRSpec Dark", "target": "", "category": "", "keywords": "", "program": 1495, "visit": 33, "observation": 1, "parallels": []}]}, {"cycle": 1, "file": "2232508f01_report_20221121.txt", "pcs_mode": "MOVING", "visit_type": "PRIME TARGETED MOVING", "start_time": "2022-11-22T18:07:44Z", "duration": "00/00:59:36", "instrument": "NIRSpec IFU Spectroscopy", "target": "SILA-NUMAN", "category": "Solar System", "keywords": "Asteroid", "program": 2418, "visit": 43, "observation": 1, "parallels": []}, {"cycle": 1, "file": "2232508f01_report_20221121.txt", "pcs_mode": "NONE", "visit_type": "PRIME UNTARGETED", "start_time": "2022-11-22T19:08:13Z", "duration": "00/00:03:53", "instrument": "NIRSpec Internal Lamp", "target": "", "category": "", "keywords": "", "program": 2777, "visit": 161, "observation": 1, "parallels": []}, {"cycle": 1, "file": "2232508f01_report_20221121.txt", "pcs_mode": "FINEGUIDE", "visit_type": "PRIME TARGETED FIXED", "start_time": "2022-11-22T19:31:28Z", "duration": "00/01:41:29", "instrument": "NIRCam Wide Field Slitless Spectroscopy", "target": "J0910P1656", "category": "Galaxy", "keywords": "High-redshift galaxies, Quasars", "program": 2078, "visit": 11, "observation": 1, "parallels": [{"cycle": 1, "file": "2232508f01_report_20221121.txt", "pcs_mode": null, "visit_type": "COORDINATED PARALLEL", "start_time": "", "duration": null, "instrument": "NIRISS Imaging", "parallels": []}]}, {"cycle": 1, "file": "2232508f01_report_20221121.txt", "pcs_mode": "NONE", "visit_type": "PRIME UNTARGETED", "start_time": "2022-11-22T21:38:57Z", "duration": "00/03:00:00", "instrument": "Realtime Commanding", "target": "", "category": "", "keywords": "", "program": 2745, "visit": 5, "observation": 1, "parallels": []}, {"cycle": 1, "file": "2232508f01_report_20221121.txt", "pcs_mode": "FINEGUIDE", "visit_type": "PRIME TARGETED FIXED", "start_time": "2022-11-23T00:57:59Z", "duration": "00/04:53:03", "instrument": "NIRCam Grism Time Series", "target": "55CNC", "category": "Star", "keywords": "Exoplanet Systems, Exoplanets, G subdwarfs", "program": 2084, "visit": 3, "observation": 1, "parallels": []}, {"cycle": 1, "file": "2232508f01_report_20221121.txt", "pcs_mode": "MOVING", "visit_type": "PRIME TARGETED MOVING", "start_time": "2022-11-23T06:57:04Z", "duration": "00/00:35:19", "instrument": "NIRCam Imaging", "target": "EUROPA", "category": "Solar System", "keywords": "Satellite", "program": 1250, "visit": 1, "observation": 1, "parallels": []}, {"cycle": 1, "file": "2232508f01_report_20221121.txt", "pcs_mode": "MOVING", "visit_type": "PRIME TARGETED MOVING", "start_time": "2022-11-23T07:40:07Z", "duration": "00/01:01:02", "instrument": "NIRSpec IFU Spectroscopy", "target": "EUROPA", "category": "Solar System", "keywords": "Satellite", "program": 1250, "visit": 2, "observation": 1, "parallels": []}, {"cycle": 1, "file": "2232508f01_report_20221121.txt", "pcs_mode": "MOVING", "visit_type": "PRIME TARGETED MOVING", "start_time": "2022-11-23T08:49:56Z", "duration": "00/00:17:40", "instrument": "MIRI Imaging", "target": "EUROPA", "category": "Solar System", "keywords": "Satellite", "program": 1250, "visit": 4, "observation": 1, "parallels": []}, {"cycle": 1, "file": "2232508f01_report_20221121.txt", "pcs_mode": "FINEGUIDE", "visit_type": "PRIME WFSC ROUTINE", "start_time": "2022-11-23T09:19:08Z", "duration": "00/01:32:08", "instrument": "WFSC NIRCam Fine Phasing", "target": "2MASS-23425655+0014229", "category": "Calibration", "keywords": "Focus test", "program": 2726, "visit": 479, "observation": 1, "parallels": []}, {"cycle": 1, "file": "2232508f01_report_20221121.txt", "pcs_mode": "MOVING", "visit_type": "PRIME TARGETED MOVING", "start_time": "2022-11-23T11:59:13Z", "duration": "00/00:43:04", "instrument": "NIRSpec IFU Spectroscopy", "target": "2003WL7", "category": "Solar System", "keywords": "Asteroid", "program": 2418, "visit": 37, "observation": 1, "parallels": []}, {"cycle": 1, "file": "2232508f01_report_20221121.txt", "pcs_mode": "MOVING", "visit_type": "PRIME TARGETED MOVING", "start_time": "2022-11-23T13:51:29Z", "duration": "00/01:03:28", "instrument": "NIRSpec IFU Spectroscopy", "target": "2000OK67", "category": "Solar System", "keywords": "Asteroid", "program": 2418, "visit": 51, "observation": 1, "parallels": []}, {"cycle": 1, "file": "2232508f01_report_20221121.txt", "pcs_mode": "MOVING", "visit_type": "PRIME TARGETED MOVING", "start_time": "2022-11-23T15:10:24Z", "duration": "00/00:59:36", "instrument": "NIRSpec IFU Spectroscopy", "target": "2005PU21", "category": "Solar System", "keywords": "Asteroid", "program": 2418, "visit": 40, "observation": 1, "parallels": []}, {"cycle": 1, "file": "2232508f01_report_20221121.txt", "pcs_mode": "FINEGUIDE", "visit_type": "PRIME TARGETED FIXED", "start_time": "2022-11-23T16:39:31Z", "duration": "00/02:58:35", "instrument": "NIRSpec IFU Spectroscopy", "target": "SDSS-J221524.00-005643.8", "category": "Galaxy", "keywords": "Quasars", "program": 2457, "visit": 1, "observation": 1, "parallels": [{"cycle": 1, "file": "2232508f01_report_20221121.txt", "pcs_mode": "NONE", "visit_type": "PARALLEL DARK CALIBRATION", "start_time": "^ATTACHED TO PRIME^", "duration": "", "instrument": "NIRCam Dark", "target": "", "category": "", "keywords": "", "program": 1483, "visit": 79, "observation": 1, "parallels": []}]}, {"cycle": 1, "file": "2232508f01_report_20221121.txt", "pcs_mode": "FINEGUIDE", "visit_type": "PRIME TARGETED FIXED", "start_time": "2022-11-23T20:46:23Z", "duration": "00/02:53:53", "instrument": "NIRSpec IFU Spectroscopy", "target": "SDSSJ0749-NIRSPEC-REPEAT", "category": "Galaxy", "keywords": "Active galactic nuclei, Emission line galaxies, Quasar-galaxy pairs", "program": 2654, "visit": 7, "observation": 1, "parallels": [{"cycle": 1, "file": "2232508f01_report_20221121.txt", "pcs_mode": "NONE", "visit_type": "PARALLEL DARK CALIBRATION", "start_time": "^ATTACHED TO PRIME^", "duration": "", "instrument": "NIRCam Dark", "target": "", "category": "", "keywords": "", "program": 1483, "visit": 124, "observation": 1, "parallels": []}]}, {"cycle": 1, "file": "2232508f01_report_20221121.txt", "pcs_mode": "FINEGUIDE", "visit_type": "PRIME TARGETED FIXED", "start_time": "2022-11-24T00:18:51Z", "duration": "00/02:34:04", "instrument": "MIRI Medium Resolution Spectroscopy", "target": "GN20-MRS", "category": "Galaxy", "keywords": "Active galactic nuclei", "program": 1264, "visit": 1, "observation": 1, "parallels": [{"cycle": 1, "file": "2232508f01_report_20221121.txt", "pcs_mode": "NONE", "visit_type": "PARALLEL DARK CALIBRATION", "start_time": "^ATTACHED TO PRIME^", "duration": "", "instrument": "NIRCam Dark", "target": "", "category": "", "keywords": "", "program": 1483, "visit": 75, "observation": 1, "parallels": []}, {"cycle": 1, "file": "2232508f01_report_20221121.txt", "pcs_mode": "NONE", "visit_type": "PARALLEL DARK CALIBRATION", "start_time": "^ATTACHED TO PRIME^", "duration": "", "instrument": "NIRSpec Dark", "target": "", "category": "", "keywords": "", "program": 1495, "visit": 34, "observation": 1, "parallels": []}]}, {"cycle": 1, "file": "2232508f01_report_20221121.txt", "pcs_mode": "FINEGUIDE", "visit_type": "PRIME TARGETED FIXED", "start_time": "2022-11-24T02:57:59Z", "duration": "00/00:41:14", "instrument": "MIRI Medium Resolution Spectroscopy", "target": "GN20-MRS-BKG", "category": "Galaxy", "keywords": "High-redshift galaxies", "program": 1264, "visit": 16, "observation": 1, "parallels": [{"cycle": 1, "file": "2232508f01_report_20221121.txt", "pcs_mode": "NONE", "visit_type": "PARALLEL DARK CALIBRATION", "start_time": "^ATTACHED TO PRIME^", "duration": "", "instrument": "NIRCam Dark", "target": "", "category": "", "keywords": "", "program": 1483, "visit": 122, "observation": 1, "parallels": []}, {"cycle": 1, "file": "2232508f01_report_20221121.txt", "pcs_mode": "NONE", "visit_type": "PARALLEL SLEW CALIBRATION", "start_time": "^ATTACHED TO PRIME^", "duration": "", "instrument": "NIRSpec Internal Lamp", "target": "", "category": "", "keywords": "", "program": 2777, "visit": 147, "observation": 1, "parallels": []}]}, {"cycle": 1, "file": "2232508f01_report_20221121.txt", "pcs_mode": "FINEGUIDE", "visit_type": "PRIME TARGETED FIXED", "start_time": "2022-11-24T04:16:52Z", "duration": "00/03:21:05", "instrument": "MIRI Medium Resolution Spectroscopy", "target": "XID2028-MIRI", "category": "Galaxy", "keywords": "Active galactic nuclei, Emission line galaxies, Quasars", "program": 1335, "visit": 5, "observation": 1, "parallels": [{"cycle": 1, "file": "2232508f01_report_20221121.txt", "pcs_mode": "NONE", "visit_type": "PARALLEL DARK CALIBRATION", "start_time": "^ATTACHED TO PRIME^", "duration": "", "instrument": "NIRSpec Dark", "target": "", "category": "", "keywords": "", "program": 1495, "visit": 35, "observation": 1, "parallels": []}]}, {"cycle": 1, "file": "2232508f01_report_20221121.txt", "pcs_mode": "FINEGUIDE", "visit_type": "PRIME TARGETED FIXED", "start_time": "2022-11-24T07:42:39Z", "duration": "00/00:53:29", "instrument": "MIRI Medium Resolution Spectroscopy", "target": "XID2028-BG", "category": "Unidentified", "keywords": "Blank field", "program": 1335, "visit": 12, "observation": 1, "parallels": [{"cycle": 1, "file": "2232508f01_report_20221121.txt", "pcs_mode": "NONE", "visit_type": "PARALLEL DARK CALIBRATION", "start_time": "^ATTACHED TO PRIME^", "duration": "", "instrument": "NIRSpec Dark", "target": "", "category": "", "keywords": "", "program": 1495, "visit": 36, "observation": 1, "parallels": []}]}, {"cycle": 1, "file": "2232508f01_report_20221121.txt", "pcs_mode": "MOVING", "visit_type": "PRIME TARGETED MOVING", "start_time": "2022-11-24T09:05:20Z", "duration": "00/01:16:36", "instrument": "NIRSpec IFU Spectroscopy", "target": "2008FC76", "category": "Solar System", "keywords": "Asteroid", "program": 1273, "visit": 7, "observation": 1, "parallels": []}, {"cycle": 1, "file": "2232508f01_report_20221121.txt", "pcs_mode": "NONE", "visit_type": "PRIME UNTARGETED", "start_time": "2022-11-24T10:22:49Z", "duration": "00/00:03:53", "instrument": "NIRSpec Internal Lamp", "target": "", "category": "", "keywords": "", "program": 2777, "visit": 80, "observation": 1, "parallels": []}, {"cycle": 1, "file": "2232508f01_report_20221121.txt", "pcs_mode": "FINEGUIDE", "visit_type": "PRIME TARGETED FIXED", "start_time": "2022-11-24T11:11:36Z", "duration": "00/06:08:01", "instrument": "NIRCam Grism Time Series", "target": "-RHO01-CNC", "category": "Star", "keywords": "G dwarfs", "program": 1952, "visit": 1, "observation": 1, "parallels": []}, {"cycle": 1, "file": "2232508f01_report_20221121.txt", "pcs_mode": "FINEGUIDE", "visit_type": "PRIME TARGETED FIXED", "start_time": "2022-11-24T18:25:23Z", "duration": "00/04:30:02", "instrument": "MIRI Imaging", "target": "TRAPPIST-1B", "category": "Star", "keywords": "Exoplanet Systems, Exoplanets, M dwarfs, M stars", "program": 1177, "visit": 9, "observation": 1, "parallels": []}, {"cycle": 1, "file": "2232508f01_report_20221121.txt", "pcs_mode": "FINEGUIDE", "visit_type": "PRIME TARGETED FIXED", "start_time": "2022-11-24T23:48:35Z", "duration": "00/01:48:37", "instrument": "MIRI Imaging", "target": "GN20-IMAGER", "category": "Galaxy", "keywords": "Active galactic nuclei, Starburst galaxies", "program": 1264, "visit": 2, "observation": 1, "parallels": [{"cycle": 1, "file": "2232508f01_report_20221121.txt", "pcs_mode": "NONE", "visit_type": "PARALLEL DARK CALIBRATION", "start_time": "^ATTACHED TO PRIME^", "duration": "", "instrument": "NIRCam Dark", "target": "", "category": "", "keywords": "", "program": 1483, "visit": 123, "observation": 1, "parallels": []}, {"cycle": 1, "file": "2232508f01_report_20221121.txt", "pcs_mode": "NONE", "visit_type": "PARALLEL DARK CALIBRATION", "start_time": "^ATTACHED TO PRIME^", "duration": "", "instrument": "NIRSpec Dark", "target": "", "category": "", "keywords": "", "program": 1495, "visit": 100, "observation": 1, "parallels": []}]}, {"cycle": 1, "file": "2232508f01_report_20221121.txt", "pcs_mode": "NONE", "visit_type": "PRIME UNTARGETED", "start_time": "2022-11-25T01:38:05Z", "duration": "00/00:01:07", "instrument": "NIRSpec Filter/Grating Wheel Test", "target": "", "category": "", "keywords": "", "program": 1496, "visit": 2, "observation": 1, "parallels": []}, {"cycle": 1, "file": "2232508f01_report_20221121.txt", "pcs_mode": "NONE", "visit_type": "PRIME UNTARGETED", "start_time": "2022-11-25T01:40:05Z", "duration": "00/00:01:07", "instrument": "NIRSpec Filter/Grating Wheel Test", "target": "", "category": "", "keywords": "", "program": 1496, "visit": 1, "observation": 1, "parallels": []}, {"cycle": 1, "file": "2232508f01_report_20221121.txt", "pcs_mode": "FINEGUIDE", "visit_type": "PRIME TARGETED FIXED", "start_time": "2022-11-25T02:03:43Z", "duration": "00/01:41:33", "instrument": "NIRSpec IFU Spectroscopy", "target": "M-81-NIRSPEC", "category": "Galaxy", "keywords": "Active galactic nuclei, Spiral galaxies", "program": 2016, "visit": 16, "observation": 1, "parallels": []}, {"cycle": 1, "file": "2232508f01_report_20221121.txt", "pcs_mode": "NONE", "visit_type": "PRIME UNTARGETED", "start_time": "2022-11-25T03:46:09Z", "duration": "00/00:03:53", "instrument": "NIRSpec Internal Lamp", "target": "", "category": "", "keywords": "", "program": 2777, "visit": 113, "observation": 1, "parallels": []}, {"cycle": 1, "file": "2232508f01_report_20221121.txt", "pcs_mode": "FINEGUIDE", "visit_type": "PRIME TARGETED FIXED", "start_time": "2022-11-25T04:11:12Z", "duration": "00/00:26:33", "instrument": "NIRSpec Fixed Slit Spectroscopy", "target": "CWISEPJ1047+54", "category": "Star", "keywords": "Brown dwarfs, Y dwarfs", "program": 2302, "visit": 125, "observation": 1, "parallels": []}, {"cycle": 1, "file": "2232508f01_report_20221121.txt", "pcs_mode": "FINEGUIDE", "visit_type": "PRIME TARGETED FIXED", "start_time": "2022-11-25T05:25:10Z", "duration": "00/04:53:03", "instrument": "NIRCam Grism Time Series", "target": "55CNC", "category": "Star", "keywords": "Exoplanet Systems, Exoplanets, G subdwarfs", "program": 2084, "visit": 4, "observation": 1, "parallels": []}, {"cycle": 1, "file": "2232508f01_report_20221121.txt", "pcs_mode": "FINEGUIDE", "visit_type": "PRIME WFSC ROUTINE", "start_time": "2022-11-25T11:23:22Z", "duration": "00/01:32:08", "instrument": "WFSC NIRCam Fine Phasing", "target": "2MASS-23425655+0014229", "category": "Calibration", "keywords": "Focus test", "program": 2726, "visit": 480, "observation": 1, "parallels": []}, {"cycle": 1, "file": "2232508f01_report_20221121.txt", "pcs_mode": "MOVING", "visit_type": "PRIME TARGETED MOVING", "start_time": "2022-11-25T13:06:49Z", "duration": "00/00:20:48", "instrument": "NIRSpec IFU Spectroscopy", "target": "CALLISTO", "category": "Solar System", "keywords": "Satellite", "program": 2060, "visit": 2, "observation": 1, "parallels": []}, {"cycle": 1, "file": "2232508f01_report_20221121.txt", "pcs_mode": "NONE", "visit_type": "PRIME UNTARGETED", "start_time": "2022-11-25T13:28:30Z", "duration": "00/00:03:53", "instrument": "NIRSpec Internal Lamp", "target": "", "category": "", "keywords": "", "program": 2777, "visit": 81, "observation": 1, "parallels": []}, {"cycle": 1, "file": "2232508f01_report_20221121.txt", "pcs_mode": "FINEGUIDE", "visit_type": "PRIME TARGETED FIXED", "start_time": "2022-11-25T14:39:54Z", "duration": "00/19:15:49", "instrument": "NIRSpec MultiObject Spectroscopy", "target": "BLUEJAY-MASTER-NORTH", "category": "", "keywords": "", "program": 1810, "visit": 1, "observation": 1, "parallels": [{"cycle": 1, "file": "2232508f01_report_20221121.txt", "pcs_mode": null, "visit_type": "COORDINATED PARALLEL", "start_time": "", "duration": null, "instrument": "NIRCam Imaging", "parallels": []}]}, {"cycle": 1, "file": "2232508f01_report_20221121.txt", "pcs_mode": "FINEGUIDE", "visit_type": "PRIME TARGETED FIXED", "start_time": "2022-11-26T10:41:05Z", "duration": "00/04:37:15", "instrument": "NIRCam Imaging", "target": "JWST-NEP-TDS-FIELD", "category": "Unidentified", "keywords": "Infrared sources, Radio sources, Variable radiation sources, Visible sources, X-ray sources", "program": 2738, "visit": 3, "observation": 1, "parallels": [{"cycle": 1, "file": "2232508f01_report_20221121.txt", "pcs_mode": null, "visit_type": "COORDINATED PARALLEL", "start_time": "", "duration": null, "instrument": "NIRISS Wide Field Slitless Spectroscopy", "parallels": []}]}, {"cycle": 1, "file": "2232508f01_report_20221121.txt", "pcs_mode": "MOVING", "visit_type": "PRIME TARGETED MOVING", "start_time": "2022-11-26T16:05:41Z", "duration": "00/00:21:08", "instrument": "NIRSpec IFU Spectroscopy", "target": "2002AW197", "category": "Solar System", "keywords": "Asteroid", "program": 1191, "visit": 12, "observation": 1, "parallels": []}, {"cycle": 1, "file": "2232508f01_report_20221121.txt", "pcs_mode": "NONE", "visit_type": "PRIME UNTARGETED", "start_time": "2022-11-26T16:27:42Z", "duration": "00/00:03:53", "instrument": "NIRSpec Internal Lamp", "target": "", "category": "", "keywords": "", "program": 2777, "visit": 160, "observation": 1, "parallels": []}, {"cycle": 1, "file": "2232508f01_report_20221121.txt", "pcs_mode": "FINEGUIDE", "visit_type": "PRIME TARGETED FIXED", "start_time": "2022-11-26T16:57:46Z", "duration": "00/01:13:52", "instrument": "MIRI Imaging", "target": "NGC-3227", "category": "Galaxy", "keywords": "Active galactic nuclei, Active galaxies, Seyfert galaxies", "program": 2064, "visit": 7, "observation": 1, "parallels": [{"cycle": 1, "file": "2232508f01_report_20221121.txt", "pcs_mode": "NONE", "visit_type": "PARALLEL DARK CALIBRATION", "start_time": "^ATTACHED TO PRIME^", "duration": "", "instrument": "NIRCam Dark", "target": "", "category": "", "keywords": "", "program": 1483, "visit": 126, "observation": 1, "parallels": []}]}, {"cycle": 1, "file": "2232508f01_report_20221121.txt", "pcs_mode": "FINEGUIDE", "visit_type": "PRIME TARGETED FIXED", "start_time": "2022-11-26T18:17:40Z", "duration": "00/00:41:32", "instrument": "MIRI Imaging", "target": "NGC-3227-BCKGND", "category": "Galaxy", "keywords": "Active galactic nuclei, Active galaxies, Seyfert galaxies", "program": 2064, "visit": 8, "observation": 1, "parallels": []}, {"cycle": 1, "file": "2232508f01_report_20221121.txt", "pcs_mode": "FINEGUIDE", "visit_type": "PRIME TARGETED FIXED", "start_time": "2022-11-26T19:15:37Z", "duration": "00/00:33:59", "instrument": "NIRSpec IFU Spectroscopy", "target": "IRAS-10565+2448", "category": "Galaxy", "keywords": "Starburst galaxies, Ultraluminous infrared galaxies", "program": 2186, "visit": 2, "observation": 1, "parallels": [{"cycle": 1, "file": "2232508f01_report_20221121.txt", "pcs_mode": "NONE", "visit_type": "PARALLEL DARK CALIBRATION", "start_time": "^ATTACHED TO PRIME^", "duration": "", "instrument": "NIRCam Dark", "target": "", "category": "", "keywords": "", "program": 1483, "visit": 80, "observation": 1, "parallels": []}]}, {"cycle": 1, "file": "2232508f01_report_20221121.txt", "pcs_mode": "NONE", "visit_type": "PRIME UNTARGETED", "start_time": "2022-11-26T19:50:29Z", "duration": "00/00:03:53", "instrument": "NIRSpec Internal Lamp", "target": "", "category": "", "keywords": "", "program": 2777, "visit": 171, "observation": 1, "parallels": []}, {"cycle": 1, "file": "2232508f01_report_20221121.txt", "pcs_mode": "FINEGUIDE", "visit_type": "PRIME TARGETED FIXED", "start_time": "2022-11-26T21:03:19Z", "duration": "00/01:09:39", "instrument": "NIRCam Coronagraphic Imaging", "target": "FOMALHAUT-C", "category": "Star", "keywords": "Debris disks, M dwarfs", "program": 1184, "visit": 9, "observation": 1, "parallels": []}, {"cycle": 1, "file": "2232508f01_report_20221121.txt", "pcs_mode": "FINEGUIDE", "visit_type": "PRIME TARGETED FIXED", "start_time": "2022-11-26T22:29:59Z", "duration": "00/01:09:39", "instrument": "NIRCam Coronagraphic Imaging", "target": "FOMALHAUT-C", "category": "Star", "keywords": "Debris disks, M dwarfs", "program": 1184, "visit": 10, "observation": 1, "parallels": []}, {"cycle": 1, "file": "2232508f01_report_20221121.txt", "pcs_mode": "FINEGUIDE", "visit_type": "PRIME TARGETED FIXED", "start_time": "2022-11-27T00:27:06Z", "duration": "00/01:09:39", "instrument": "NIRCam Coronagraphic Imaging", "target": "V-AP-COL", "category": "Star", "keywords": "M dwarfs", "program": 1184, "visit": 11, "observation": 1, "parallels": []}, {"cycle": 1, "file": "2232508f01_report_20221121.txt", "pcs_mode": "FINEGUIDE", "visit_type": "PRIME TARGETED FIXED", "start_time": "2022-11-27T01:53:46Z", "duration": "00/01:09:39", "instrument": "NIRCam Coronagraphic Imaging", "target": "V-AP-COL", "category": "Star", "keywords": "M dwarfs", "program": 1184, "visit": 12, "observation": 1, "parallels": []}, {"cycle": 1, "file": "2232508f01_report_20221121.txt", "pcs_mode": "FINEGUIDE", "visit_type": "PRIME TARGETED FIXED", "start_time": "2022-11-27T03:39:52Z", "duration": "00/01:09:39", "instrument": "NIRCam Coronagraphic Imaging", "target": "2MJ0944", "category": "Star", "keywords": "M dwarfs", "program": 1184, "visit": 13, "observation": 1, "parallels": []}, {"cycle": 1, "file": "2232508f01_report_20221121.txt", "pcs_mode": "FINEGUIDE", "visit_type": "PRIME TARGETED FIXED", "start_time": "2022-11-27T05:17:04Z", "duration": "00/01:09:39", "instrument": "NIRCam Coronagraphic Imaging", "target": "2MJ0944", "category": "Star", "keywords": "M dwarfs", "program": 1184, "visit": 14, "observation": 1, "parallels": []}, {"cycle": 1, "file": "2232508f01_report_20221121.txt", "pcs_mode": "FINEGUIDE", "visit_type": "PRIME TARGETED FIXED", "start_time": "2022-11-27T07:33:24Z", "duration": "00/04:46:30", "instrument": "NIRISS Single-Object Slitless Spectroscopy", "target": "WASP-52", "category": "Star", "keywords": "Exoplanet Systems, Exoplanets", "program": 1201, "visit": 501, "observation": 1, "parallels": []}, {"cycle": 1, "file": "2232508f01_report_20221121.txt", "pcs_mode": "FINEGUIDE", "visit_type": "PRIME WFSC ROUTINE", "start_time": "2022-11-27T13:01:29Z", "duration": "00/01:32:08", "instrument": "WFSC NIRCam Fine Phasing", "target": "2MASS-17505832+6914281", "category": "Calibration", "keywords": "Focus test", "program": 2725, "visit": 482, "observation": 1, "parallels": []}, {"cycle": 1, "file": "2232508f01_report_20221121.txt", "pcs_mode": "FINEGUIDE", "visit_type": "PRIME TARGETED FIXED", "start_time": "2022-11-27T14:44:58Z", "duration": "00/04:37:15", "instrument": "NIRCam Imaging", "target": "JWST-NEP-TDS-FIELD", "category": "Unidentified", "keywords": "Infrared sources, Radio sources, Variable radiation sources, Visible sources, X-ray sources", "program": 2738, "visit": 3, "observation": 2, "parallels": [{"cycle": 1, "file": "2232508f01_report_20221121.txt", "pcs_mode": null, "visit_type": "COORDINATED PARALLEL", "start_time": "", "duration": null, "instrument": "NIRISS Wide Field Slitless Spectroscopy", "parallels": []}]}, {"cycle": 1, "file": "2232508f01_report_20221121.txt", "pcs_mode": "FINEGUIDE", "visit_type": "PRIME TARGETED FIXED", "start_time": "2022-11-27T20:01:30Z", "duration": "00/00:49:17", "instrument": "NIRCam Coronagraphic Imaging", "target": "HR8799", "category": "Star", "keywords": "Exoplanet Systems", "program": 1194, "visit": 1, "observation": 1, "parallels": []}, {"cycle": 1, "file": "2232508f01_report_20221121.txt", "pcs_mode": "FINEGUIDE", "visit_type": "PRIME TARGETED FIXED", "start_time": "2022-11-27T21:02:49Z", "duration": "00/00:42:16", "instrument": "NIRCam Coronagraphic Imaging", "target": "HD220657", "category": "Calibration", "keywords": "Coronagraphic", "program": 1194, "visit": 3, "observation": 1, "parallels": []}, {"cycle": 1, "file": "2232508f01_report_20221121.txt", "pcs_mode": "FINEGUIDE", "visit_type": "PRIME TARGETED FIXED", "start_time": "2022-11-27T22:02:46Z", "duration": "00/00:49:17", "instrument": "NIRCam Coronagraphic Imaging", "target": "HR8799", "category": "Star", "keywords": "Exoplanet Systems", "program": 1194, "visit": 6, "observation": 1, "parallels": []}, {"cycle": 1, "file": "2232508f01_report_20221121.txt", "pcs_mode": "MOVING", "visit_type": "PRIME TARGETED MOVING", "start_time": "2022-11-27T23:56:47Z", "duration": "00/00:54:31", "instrument": "NIRSpec Fixed Slit Spectroscopy", "target": "824ANASTASIA", "category": "Solar System", "keywords": "Asteroid", "program": 2361, "visit": 8, "observation": 1, "parallels": []}, {"cycle": 1, "file": "2232508f01_report_20221121.txt", "pcs_mode": "MOVING", "visit_type": "PRIME TARGETED MOVING", "start_time": "2022-11-28T01:16:11Z", "duration": "00/00:23:39", "instrument": "NIRSpec Fixed Slit Spectroscopy", "target": "DIDYMOS", "category": "Solar System", "keywords": "Asteroid", "program": 1245, "visit": 20, "observation": 1, "parallels": []}, {"cycle": 1, "file": "2232508f01_report_20221121.txt", "pcs_mode": "FINEGUIDE", "visit_type": "PRIME TARGETED FIXED", "start_time": "2022-11-28T02:09:17Z", "duration": "00/01:41:29", "instrument": "NIRCam Wide Field Slitless Spectroscopy", "target": "J1104P2134", "category": "Galaxy", "keywords": "High-redshift galaxies, Quasars", "program": 2078, "visit": 18, "observation": 1, "parallels": [{"cycle": 1, "file": "2232508f01_report_20221121.txt", "pcs_mode": null, "visit_type": "COORDINATED PARALLEL", "start_time": "", "duration": null, "instrument": "NIRISS Imaging", "parallels": []}]}, {"cycle": 1, "file": "2232508f01_report_20221121.txt", "pcs_mode": "FINEGUIDE", "visit_type": "PRIME TARGETED FIXED", "start_time": "2022-11-28T04:26:46Z", "duration": "00/02:20:07", "instrument": "NIRSpec Fixed Slit Spectroscopy", "target": "NGC2506G31", "category": "Star", "keywords": "G dwarfs", "program": 1538, "visit": 32, "observation": 1, "parallels": [{"cycle": 1, "file": "2232508f01_report_20221121.txt", "pcs_mode": "NONE", "visit_type": "PARALLEL DARK CALIBRATION", "start_time": "^ATTACHED TO PRIME^", "duration": "", "instrument": "NIRCam Dark", "target": "", "category": "", "keywords": "", "program": 1483, "visit": 70, "observation": 1, "parallels": []}]}, {"cycle": 1, "file": "2232508f01_report_20221121.txt", "pcs_mode": "FINEGUIDE", "visit_type": "PRIME TARGETED FIXED", "start_time": "2022-11-28T07:07:52Z", "duration": "00/01:13:22", "instrument": "NIRSpec Fixed Slit Spectroscopy", "target": "J0844-0132", "category": "Galaxy", "keywords": "High-redshift galaxies, Quasars", "program": 1967, "visit": 3, "observation": 1, "parallels": [{"cycle": 1, "file": "2232508f01_report_20221121.txt", "pcs_mode": "NONE", "visit_type": "PARALLEL DARK CALIBRATION", "start_time": "^ATTACHED TO PRIME^", "duration": "", "instrument": "NIRCam Dark", "target": "", "category": "", "keywords": "", "program": 1483, "visit": 74, "observation": 1, "parallels": []}]}, {"cycle": 1, "file": "2232508f01_report_20221121.txt", "pcs_mode": "FINEGUIDE", "visit_type": "PRIME TARGETED FIXED", "start_time": "2022-11-28T08:28:34Z", "duration": "00/01:26:32", "instrument": "NIRCam Imaging", "target": "J0844-0132", "category": "Galaxy", "keywords": "High-redshift galaxies, Quasars", "program": 1967, "visit": 15, "observation": 1, "parallels": [{"cycle": 1, "file": "2232508f01_report_20221121.txt", "pcs_mode": "NONE", "visit_type": "PARALLEL DARK CALIBRATION", "start_time": "^ATTACHED TO PRIME^", "duration": "", "instrument": "NIRSpec Dark", "target": "", "category": "", "keywords": "", "program": 1495, "visit": 101, "observation": 1, "parallels": []}]}, {"cycle": 1, "file": "2232508f01_report_20221121.txt", "pcs_mode": "MOVING", "visit_type": "PRIME TARGETED MOVING", "start_time": "2022-11-28T10:24:52Z", "duration": "00/01:18:04", "instrument": "NIRSpec IFU Spectroscopy", "target": "LEMMON", "category": "Solar System", "keywords": "Comet", "program": 2416, "visit": 7, "observation": 1, "parallels": []}, {"cycle": 1, "file": "2232508f01_report_20221121.txt", "pcs_mode": "MOVING", "visit_type": "PRIME TARGETED MOVING", "start_time": "2022-11-28T11:49:24Z", "duration": "00/01:15:19", "instrument": "NIRSpec IFU Spectroscopy", "target": "LEMMON-OFFSET", "category": "Solar System", "keywords": "Comet", "program": 2416, "visit": 8, "observation": 1, "parallels": []}, {"cycle": 1, "file": "2232508f01_report_20221121.txt", "pcs_mode": "NONE", "visit_type": "PRIME UNTARGETED", "start_time": "2022-11-28T13:05:36Z", "duration": "00/00:03:53", "instrument": "NIRSpec Internal Lamp", "target": "", "category": "", "keywords": "", "program": 2777, "visit": 158, "observation": 1, "parallels": []}]